opensubtitles_dataloader/__init__.py
opensubtitles_dataloader/__main__.py
opensubtitles_dataloader-0.1.4.dist-info/entry_points.txt
opensubtitles_dataloader-0.1.4.dist-info/WHEEL
opensubtitles_dataloader-0.1.4.dist-info/METADATA
opensubtitles_dataloader-0.1.4.dist-info/RECORD
