Metadata-Version: 2.1
Name: opensubtitles-dataloader
Version: 0.1.4
Summary: 
Author: Christoph Minixhofer
Author-email: christoph.minixhofer@gmail.com
Requires-Python: >=3.5,<4.0
Classifier: Programming Language :: Python :: 3
Classifier: Programming Language :: Python :: 3.5
Classifier: Programming Language :: Python :: 3.6
Classifier: Programming Language :: Python :: 3.7
Classifier: Programming Language :: Python :: 3.8
Requires-Dist: click (>=7.1.2,<8.0.0)
Requires-Dist: numpy (>=1.0,<2.0)
Requires-Dist: torch (>=1.0,<2.0)
Requires-Dist: tqdm (>=4.0,<5.0)
